{
  "timestamp": "2025-09-26 13:33:59 UTC",
  "signals": [
    {
      "ticker": "GLW",
      "company": "Corning Incorporated",
      "days_since": 1,
      "last_price": 79.35
    },
    {
      "ticker": "VNO",
      "company": "Vornado Realty Trust",
      "days_since": 0,
      "last_price": 40.16
    },
    {
      "ticker": "PG",
      "company": "The Procter & Gamble Company",
      "days_since": 2,
      "last_price": 152.52
    },
    {
      "ticker": "T",
      "company": "AT&T Inc.",
      "days_since": 2,
      "last_price": 28.45
    },
    {
      "ticker": "NDAQ",
      "company": "Nasdaq, Inc.",
      "days_since": 2,
      "last_price": 87.31
    },
    {
      "ticker": "NVR",
      "company": "NVR, Inc.",
      "days_since": 2,
      "last_price": 7906.69
    },
    {
      "ticker": "MA",
      "company": "Mastercard Incorporated",
      "days_since": 2,
      "last_price": 566.84
    },
    {
      "ticker": "ALLY",
      "company": "Ally Financial Inc.",
      "days_since": 0,
      "last_price": 40.87
    },
    {
      "ticker": "VNO",
      "company": "Vornado Realty Trust",
      "days_since": 0,
      "last_price": 40.02
    },
    {
      "ticker": "KIM",
      "company": "Kimco Realty Corporation",
      "days_since": 1,
      "last_price": 21.55
    },
    {
      "ticker": "GL",
      "company": "Globe Life Inc.",
      "days_since": 1,
      "last_price": 143.92
    },
    {
      "ticker": "UAL",
      "company": "United Airlines Holdings, Inc.",
      "days_since": 1,
      "last_price": 99.66
    }
  ]
}