{
  "timestamp": "2025-09-19 09:27:58 UTC",
  "signals": [
    {
      "ticker": "FRT",
      "company": "Federal Realty Investment Trust",
      "days_since": 1,
      "last_price": 100.22
    },
    {
      "ticker": "DB1.DE",
      "company": "Deutsche B\u00f6rse AG",
      "days_since": 0,
      "last_price": 230.7
    },
    {
      "ticker": "ROL",
      "company": "Rollins, Inc.",
      "days_since": 2,
      "last_price": 55.73
    },
    {
      "ticker": "CB",
      "company": "Chubb Limited",
      "days_since": 2,
      "last_price": 274.28
    },
    {
      "ticker": "ATO",
      "company": "Atmos Energy Corporation",
      "days_since": 0,
      "last_price": 162.44
    },
    {
      "ticker": "DTE.DE",
      "company": "Deutsche Telekom AG",
      "days_since": 1,
      "last_price": 29.23
    },
    {
      "ticker": "NDAQ",
      "company": "Nasdaq, Inc.",
      "days_since": 0,
      "last_price": 88.87
    },
    {
      "ticker": "BSX",
      "company": "Boston Scientific Corporation",
      "days_since": 0,
      "last_price": 98.23
    },
    {
      "ticker": "EG",
      "company": "Everest Group, Ltd.",
      "days_since": 1,
      "last_price": 334.75
    },
    {
      "ticker": "PRU",
      "company": "Prudential Financial, Inc.",
      "days_since": 2,
      "last_price": 103.87
    },
    {
      "ticker": "HOLX",
      "company": "Hologic, Inc.",
      "days_since": 2,
      "last_price": 68.27
    },
    {
      "ticker": "DAY",
      "company": "Dayforce Inc",
      "days_since": 1,
      "last_price": 68.95
    },
    {
      "ticker": "KIM",
      "company": "Kimco Realty Corporation",
      "days_since": 1,
      "last_price": 22.17
    },
    {
      "ticker": "UAL",
      "company": "United Airlines Holdings, Inc.",
      "days_since": 2,
      "last_price": 105.38
    }
  ]
}